caikit/__init__.py
caikit/_version.py
caikit/version.py
caikit/config/__init__.py
caikit/config/config.py
caikit/config/config.yml
caikit/core/__init__.py
caikit/core/model_manager.py
caikit/core/registries.py
caikit/core/task.py
caikit/core/augmentors/__init__.py
caikit/core/augmentors/base.py
caikit/core/augmentors/merged_augmentor.py
caikit/core/augmentors/schemes/__init__.py
caikit/core/augmentors/schemes/always_selection_scheme.py
caikit/core/augmentors/schemes/base.py
caikit/core/augmentors/schemes/random_multi_selection_scheme.py
caikit/core/augmentors/schemes/random_single_selection_scheme.py
caikit/core/data_model/__init__.py
caikit/core/data_model/base.py
caikit/core/data_model/dataobject.py
caikit/core/data_model/enums.py
caikit/core/data_model/job.py
caikit/core/data_model/json_dict.py
caikit/core/data_model/package.py
caikit/core/data_model/prediction_status.py
caikit/core/data_model/producer.py
caikit/core/data_model/runtime_context.py
caikit/core/data_model/timestamp.py
caikit/core/data_model/training_status.py
caikit/core/data_model/data_backends/__init__.py
caikit/core/data_model/data_backends/base.py
caikit/core/data_model/data_backends/dict_backend.py
caikit/core/data_model/protobufs/__init__.py
caikit/core/data_model/streams/__init__.py
caikit/core/data_model/streams/converter.py
caikit/core/data_model/streams/csv_column_formatter.py
caikit/core/data_model/streams/data_stream.py
caikit/core/data_model/streams/multipart_decoder.py
caikit/core/data_model/streams/resolver.py
caikit/core/data_model/streams/validator.py
caikit/core/exceptions/__init__.py
caikit/core/exceptions/caikit_core_exception.py
caikit/core/exceptions/error_handler.py
caikit/core/exceptions/validation_error.py
caikit/core/model_management/__init__.py
caikit/core/model_management/factories.py
caikit/core/model_management/job_base.py
caikit/core/model_management/job_predictor_base.py
caikit/core/model_management/local_job_base.py
caikit-0.28.3.dist-info/licenses/LICENSE
caikit-0.28.3.dist-info/METADATA
caikit-0.28.3.dist-info/WHEEL
caikit-0.28.3.dist-info/entry_points.txt
caikit-0.28.3.dist-info/top_level.txt
caikit-0.28.3.dist-info/RECORD
