Metadata-Version: 2.4
Name: caikit
Version: 0.28.3
Summary: AI toolkit that enables AI users to consume stable task-specific model APIs and enables AI developers build algorithms and models in a modular/composable framework
License: Apache-2.0
Project-URL: Source, https://github.com/caikit/caikit
Classifier: License :: OSI Approved :: Apache Software License
Requires-Python: >=3.8
License-File: LICENSE
Requires-Dist: alchemy-config<2.0.0,>=1.1.1
Requires-Dist: alchemy-logging<2.0.0,>=1.3.2
Requires-Dist: anytree<3.0,>=2.7.0
Requires-Dist: docstring-parser<0.17.0,>=0.14.1
Requires-Dist: grpcio!=1.55.0,!=1.64.0,<3.0,>=1.35.0
Requires-Dist: ijson<3.3.0,>=3.1.4
Requires-Dist: importlib-metadata<8.0.0,>=6.8.0
Requires-Dist: munch<5.0,>=2.5.0
Requires-Dist: numpy<3,>=1.22.2
Requires-Dist: protobuf<7,>=4
Requires-Dist: psutil<6,>=5
Requires-Dist: py-to-proto!=0.2.1,<0.7.0,>=0.5.0
Requires-Dist: PyYAML<7.0,>=6.0
Requires-Dist: semver<4.0,>=2.13.0
Requires-Dist: six<2.0.0,>=1.16.0
Requires-Dist: tqdm<5.0.0,>=4.59.0
Requires-Dist: werkzeug<4.0.0,>=2.3.7
Provides-Extra: runtime-grpc
Requires-Dist: grpcio-health-checking; extra == "runtime-grpc"
Requires-Dist: grpcio-reflection; extra == "runtime-grpc"
Requires-Dist: prometheus_client; extra == "runtime-grpc"
Requires-Dist: py-grpc-prometheus; extra == "runtime-grpc"
Provides-Extra: runtime-http
Requires-Dist: fastapi[all]<1,>=0.100; extra == "runtime-http"
Requires-Dist: pydantic<3,>=2.8.0; extra == "runtime-http"
Requires-Dist: requests<3,>=2.28.2; extra == "runtime-http"
Requires-Dist: sse-starlette<3,>=1.6.1; extra == "runtime-http"
Requires-Dist: typing_extensions<5,>=4.12.0; extra == "runtime-http"
Provides-Extra: runtime-client
Requires-Dist: requests<3,>=2.28.2; extra == "runtime-client"
Provides-Extra: runtime-trace
Requires-Dist: opentelemetry-sdk<2,>=1.24.0; extra == "runtime-trace"
Requires-Dist: opentelemetry-exporter-otlp<2,>=1.24.0; extra == "runtime-trace"
Provides-Extra: interfaces-vision
Requires-Dist: pillow<11.0,>=6.2.1; extra == "interfaces-vision"
Provides-Extra: interfaces-ts
Requires-Dist: pandas<2,>=1.4.3; extra == "interfaces-ts"
Provides-Extra: interfaces-ts-pyspark
Requires-Dist: caikit[interfaces-ts]; extra == "interfaces-ts-pyspark"
Requires-Dist: pyspark<3.6,>=3.3; extra == "interfaces-ts-pyspark"
Requires-Dist: pyarrow<16,>=8.0.0; extra == "interfaces-ts-pyspark"
Provides-Extra: all
Requires-Dist: caikit[interfaces-ts,interfaces-vision,runtime-client,runtime-grpc,runtime-http,runtime-trace]; extra == "all"
Provides-Extra: dev-test
Requires-Dist: pytest-asyncio<0.22,>=0.21.0; extra == "dev-test"
Requires-Dist: pytest-cov<6.0,>=2.10.1; extra == "dev-test"
Requires-Dist: pytest-html<5.0,>=3.1.1; extra == "dev-test"
Requires-Dist: pytest<8.0,>=6.2.5; extra == "dev-test"
Requires-Dist: tls_test_tools>=0.1.1; extra == "dev-test"
Requires-Dist: wheel>=0.38.4; extra == "dev-test"
Requires-Dist: caikit[interfaces-ts-pyspark,interfaces-vision,runtime-client]; extra == "dev-test"
Provides-Extra: dev-docs
Requires-Dist: sphinx<8.0,>=4.0.2; extra == "dev-docs"
Requires-Dist: sphinx-autoapi>=2.1.0; extra == "dev-docs"
Requires-Dist: sphinx-rtd-theme<2.1.0,>=1.2.1; extra == "dev-docs"
Provides-Extra: dev-fmt
Requires-Dist: ruff==0.4.7; extra == "dev-fmt"
Requires-Dist: pre-commit<4.0,>=3.0.4; extra == "dev-fmt"
Requires-Dist: pydeps<2,>=1.12.12; extra == "dev-fmt"
Provides-Extra: dev-build
Requires-Dist: flit==3.9.0; extra == "dev-build"
Provides-Extra: all-dev
Requires-Dist: caikit[all,dev-build,dev-docs,dev-fmt,dev-test]; extra == "all-dev"
Dynamic: license-file
